<?xml version="1.0" encoding="UTF-8"?>
<odoo>

	    
	     
    <record model="ir.ui.view" id="view_purchase_oder_form">
        <field name="name">purchase.oder.form</field>
        <field name="model">purchase.oder</field>
        <field name="type">form</field>
        <field name="arch" type="xml">
            <form string="purchase.oder">

            </form>
        </field>
    </record>
    <record model="ir.ui.view" id="view_purchase_oder_tree">
        <field name="name">purchase.oder.tree</field>
        <field name="model">purchase.oder</field>
        <field name="type">tree</field>
        <field name="arch" type="xml">
            <tree string="purchase.oder">

            </tree>
        </field>
    </record>
    <record model="ir.actions.act_window" id="action_purchase_oder">
        <field name="name">purchase_oder</field>
        <field name="res_model">purchase.oder</field>

        <field name="view_mode">tree,form</field>
    </record>
    <menuitem name="Unknown/purchase_oder" id="menu_purchase_oder" action="action_purchase_oder"/>
     
	 

</odoo>
